[
  {
    "task_id": "task-cs-pset-4",
    "title": "CS 340 Problem Set 4",
    "course": "CS 340",
    "task_type": "problem_set",
    "estimate_hours": 3.0,
    "corrected_effort_hours": 6.0,
    "hours_until_due": 30.0,
    "start_delay_hours": 14.0,
    "status": "todo",
    "due_date": "2026-04-08T23:59:00Z",
    "course_snapshot": {
      "code_module": "BBB",
      "code_presentation": "2014J",
      "highest_education": "A Level or Equivalent",
      "age_band": "0-35",
      "imd_band": "20-30%",
      "studied_credits": 120,
      "num_of_prev_attempts": 1,
      "disability": "N",
      "gender": "F",
      "days_registered_before_start": 38,
      "module_presentation_length": 269,
      "unregistered_by_day_30": 0,
      "day_of_unregistration_capped": 31,
      "assessments_due_30d": 2,
      "assessments_submitted_30d": 1,
      "assessment_mean_score_30d": 42,
      "weighted_score_pct_30d": 19,
      "missing_submissions_30d": 1,
      "late_submissions_30d": 1,
      "total_clicks_30d": 54,
      "active_days_30d": 7,
      "unique_sites_30d": 10,
      "unique_activity_types_30d": 4,
      "pre_start_clicks": 3,
      "post_start_clicks": 51,
      "clicks_resource": 12,
      "clicks_oucontent": 18,
      "clicks_subpage": 8,
      "clicks_url": 5,
      "clicks_forumng": 6,
      "clicks_quiz": 5
    },
    "personalization_signals": {
      "recent_completion_rate": 0.42,
      "recent_overdue_count": 2,
      "start_lag_hours": 11,
      "focus_block_accept_rate": 0.55,
      "focus_block_completion_rate": 0.38
    }
  },
  {
    "task_id": "task-stat-quiz",
    "title": "STAT 301 Quiz Prep",
    "course": "STAT 301",
    "task_type": "quiz",
    "estimate_hours": 1.5,
    "corrected_effort_hours": 2.4,
    "hours_until_due": 18.0,
    "start_delay_hours": 6.0,
    "status": "in_progress",
    "due_date": "2026-04-07T16:00:00Z",
    "course_snapshot": {
      "code_module": "CCC",
      "code_presentation": "2014B",
      "highest_education": "HE Qualification",
      "age_band": "35-55",
      "imd_band": "50-60%",
      "studied_credits": 60,
      "num_of_prev_attempts": 0,
      "disability": "N",
      "gender": "M",
      "days_registered_before_start": 62,
      "module_presentation_length": 241,
      "unregistered_by_day_30": 0,
      "day_of_unregistration_capped": 31,
      "assessments_due_30d": 1,
      "assessments_submitted_30d": 1,
      "assessment_mean_score_30d": 71,
      "weighted_score_pct_30d": 68,
      "missing_submissions_30d": 0,
      "late_submissions_30d": 0,
      "total_clicks_30d": 188,
      "active_days_30d": 18,
      "unique_sites_30d": 22,
      "unique_activity_types_30d": 6,
      "pre_start_clicks": 12,
      "post_start_clicks": 176,
      "clicks_resource": 44,
      "clicks_oucontent": 58,
      "clicks_subpage": 23,
      "clicks_url": 21,
      "clicks_forumng": 19,
      "clicks_quiz": 23
    },
    "personalization_signals": {
      "recent_completion_rate": 0.74,
      "recent_overdue_count": 0,
      "start_lag_hours": 3,
      "focus_block_accept_rate": 0.82,
      "focus_block_completion_rate": 0.71
    }
  },
  {
    "task_id": "task-design-reading",
    "title": "Design reading response",
    "course": "DES 210",
    "task_type": "reading",
    "estimate_hours": 1.0,
    "corrected_effort_hours": 1.3,
    "hours_until_due": 44.0,
    "start_delay_hours": 2.0,
    "status": "todo",
    "due_date": "2026-04-10T18:00:00Z",
    "course_snapshot": {
      "code_module": "EEE",
      "code_presentation": "2014J",
      "highest_education": "A Level or Equivalent",
      "age_band": "0-35",
      "imd_band": "70-80%",
      "studied_credits": 60,
      "num_of_prev_attempts": 0,
      "disability": "N",
      "gender": "F",
      "days_registered_before_start": 44,
      "module_presentation_length": 252,
      "unregistered_by_day_30": 0,
      "day_of_unregistration_capped": 31,
      "assessments_due_30d": 1,
      "assessments_submitted_30d": 1,
      "assessment_mean_score_30d": 79,
      "weighted_score_pct_30d": 74,
      "missing_submissions_30d": 0,
      "late_submissions_30d": 0,
      "total_clicks_30d": 236,
      "active_days_30d": 20,
      "unique_sites_30d": 24,
      "unique_activity_types_30d": 6,
      "pre_start_clicks": 10,
      "post_start_clicks": 226,
      "clicks_resource": 58,
      "clicks_oucontent": 69,
      "clicks_subpage": 29,
      "clicks_url": 25,
      "clicks_forumng": 27,
      "clicks_quiz": 28
    },
    "personalization_signals": {
      "recent_completion_rate": 0.81,
      "recent_overdue_count": 0,
      "start_lag_hours": 1,
      "focus_block_accept_rate": 0.84,
      "focus_block_completion_rate": 0.8
    }
  }
]
